CHANGES.txt
README.txt
bootstrap.py
buildout.cfg
setup.py
collective/__init__.py
collective.recipe.shelloutput.egg-info/PKG-INFO
collective.recipe.shelloutput.egg-info/SOURCES.txt
collective.recipe.shelloutput.egg-info/dependency_links.txt
collective.recipe.shelloutput.egg-info/entry_points.txt
collective.recipe.shelloutput.egg-info/namespace_packages.txt
collective.recipe.shelloutput.egg-info/not-zip-safe
collective.recipe.shelloutput.egg-info/requires.txt
collective.recipe.shelloutput.egg-info/requires.txt~
collective.recipe.shelloutput.egg-info/top_level.txt
collective/recipe/__init__.py
collective/recipe/shelloutput/README.txt
collective/recipe/shelloutput/__init__.py
collective/recipe/shelloutput/tests/__init__.py
collective/recipe/shelloutput/tests/test_docs.py