Metadata-Version: 1.0
Name: collective.recipe.shelloutput
Version: 0.1
Summary: Execute shell commands and reuse the output in another part of the buildout.
Home-page: http://svn.plone.org/svn/collective/
Author: j23d
Author-email: m@s3edv.de
License: ZPL
Keywords: shell recipe
Platform: UNKNOWN
Classifier: Framework :: Buildout
Classifier: Intended Audience :: Developers
Classifier: Topic :: Software Development :: Build Tools
Classifier: License :: OSI Approved :: Zope Public License
